mycursordata/__init__.py
mycursordata/cli.py
mycursordata/discovery.py
mycursordata/parser.py
mycursordata/tool_calls.py
mycursordata-0.1.0.dist-info/METADATA
mycursordata-0.1.0.dist-info/WHEEL
mycursordata-0.1.0.dist-info/entry_points.txt
mycursordata-0.1.0.dist-info/licenses/LICENSE
mycursordata-0.1.0.dist-info/RECORD
