Metadata-Version: 2.4
Name: mycursordata
Version: 0.1.0
Summary: Extract and export your Cursor IDE conversation history
Project-URL: Homepage, https://github.com/joancabezas/mycursordata
Project-URL: Repository, https://github.com/joancabezas/mycursordata
Project-URL: Issues, https://github.com/joancabezas/mycursordata/issues
Author-email: Joan Cabezas <joan.santiago.cabezas@gmail.com>
License: MIT
License-File: LICENSE
Keywords: ai,chat,conversations,cursor,export,ide,sqlite
Classifier: Development Status :: 4 - Beta
Classifier: Environment :: Console
Classifier: Intended Audience :: Developers
Classifier: License :: OSI Approved :: MIT License
Classifier: Operating System :: OS Independent
Classifier: Programming Language :: Python :: 3
Classifier: Programming Language :: Python :: 3.11
Classifier: Programming Language :: Python :: 3.12
Classifier: Programming Language :: Python :: 3.13
Classifier: Topic :: Software Development :: Documentation
Classifier: Topic :: Utilities
Requires-Python: >=3.11
